bol/__init__.py
bol/client.py
bol-1.3.2.dist-info/LICENSE
bol-1.3.2.dist-info/METADATA
bol-1.3.2.dist-info/WHEEL
bol-1.3.2.dist-info/top_level.txt
bol-1.3.2.dist-info/RECORD
