Metadata-Version: 2.1
Name: bol
Version: 1.3.2
Summary: A bol.com api connector
Home-page: https://gitlab.com/aapjeisbaas/bol
Author: Stein van Broekhoven
Author-email: stein@aapjeisbaas.nl
Classifier: Programming Language :: Python :: 3
Classifier: License :: OSI Approved :: MIT License
Classifier: Operating System :: OS Independent
Requires-Python: >=3.6
License-File: LICENSE
Requires-Dist: requests
